{
  "version": "1",
  "cognitoConfig": {
    "identityPoolName": "formfiller86c3f317_identitypool_86c3f317",
    "allowUnauthenticatedIdentities": false,
    "resourceNameTruncated": "formfi86c3f317",
    "userPoolName": "formfiller86c3f317_userpool_86c3f317",
    "autoVerifiedAttributes": [
      "email"
    ],
    "mfaConfiguration": "OFF",
    "mfaTypes": [
      "SMS Text Message"
    ],
    "smsAuthenticationMessage": "Your authentication code is {####}",
    "smsVerificationMessage": "Your verification code is {####}",
    "emailVerificationSubject": "Your verification code",
    "emailVerificationMessage": "Your verification code is {####}",
    "defaultPasswordPolicy": false,
    "passwordPolicyMinLength": 8,
    "passwordPolicyCharacters": [],
    "requiredAttributes": [
      "email"
    ],
    "aliasAttributes": [],
    "userpoolClientGenerateSecret": false,
    "userpoolClientRefreshTokenValidity": 30,
    "userpoolClientWriteAttributes": [
      "email"
    ],
    "userpoolClientReadAttributes": [
      "email"
    ],
    "userpoolClientLambdaRole": "formfi86c3f317_userpoolclient_lambda_role",
    "userpoolClientSetAttributes": false,
    "sharedId": "86c3f317",
    "resourceName": "formfiller86c3f317",
    "authSelections": "identityPoolAndUserPool",
    "useDefault": "default",
    "usernameAttributes": [
      "email, phone_number"
    ],
    "userPoolGroupList": [],
    "serviceName": "Cognito",
    "usernameCaseSensitive": false,
    "useEnabledMfas": true
  }
}